{
  "required": true,
  "package": "survivalblock.crossbow_scoping.mixin",
  "compatibilityLevel": "JAVA_21",
  "mixins": [
    "crossbow.CrossbowItemMixin",
    "crossbow.ItemMixin",
    "crossbow.LivingEntityMixin",
    "crossbow.PlayerEntityMixin",
    "crossbow.PlayerInventoryMixin",
    "crossbow.RangedWeaponItemMixin",
    "crossbow.ServerPlayNetworkHandlerMixin",
    "crossbow.TypedActionResultAccessor"
  ],
  "client": [
    "crossbow.client.InGameHudMixin",
    "crossbow.client.ItemRendererMixin",
    "crossbow.client.MinecraftClientMixin",
    "crossbow.client.PlayerHeldItemFeatureRendererMixin"
  ],
  "injectors": {
    "defaultRequire": 1
  }
}